paprica/__init__.py
paprica/_version.py
paprica/atlaser.py
paprica/batcher.py
paprica/converter.py
paprica/loader.py
paprica/parser.py
paprica/runner.py
paprica/segmenter.py
paprica/stitcher.py
paprica/viewer.py
paprica-0.0.1.dist-info/METADATA
paprica-0.0.1.dist-info/WHEEL
paprica-0.0.1.dist-info/top_level.txt
paprica-0.0.1.dist-info/RECORD
