Metadata-Version: 2.1
Name: paprica
Version: 0.0.1
Summary: APR-based image processing pipeline for microscopy data
Home-page: https://github.com/WyssCenter/pAPRica
Author: Jules Scholler, Joel Jonsson
Author-email: jules.scholler@wysscenter.ch, jonsson@mpi-cbg.de
License: LIMITED LICENSE AGREEMENT
Keywords: APR,adaptive,image,representation,processing,pipeline,registration,segmentation,stitching
Classifier: Development Status :: 1 - Planning
Classifier: Intended Audience :: Developers
Classifier: Programming Language :: Python :: 3
Requires-Dist: numpy
Requires-Dist: scipy
Requires-Dist: pyapr
Requires-Dist: tqdm
Requires-Dist: pandas
Requires-Dist: scikit-image
Requires-Dist: scikit-learn
Requires-Dist: opencv-contrib-python-headless
Requires-Dist: dill
Requires-Dist: matplotlib
Requires-Dist: napari
Requires-Dist: allensdk
Requires-Dist: sparse
Requires-Dist: brainreg
Requires-Dist: joblib
Requires-Dist: pytest
